positive/__init__.py
positive/api.py
positive/io.py
positive/learning.py
positive/maths.py
positive/physics.py
positive/plotting.py
positive/strings.py
positive/units.py
positive/data/berti_kerrcw_fitcoeffsWEB.dat
positive/data/berti_swsh_fits.dat
positive/data/cwmodels.pickle
positive/data/ksm2_cw.py
positive/data/ksm2_cw.pyc
positive/data/ysmodels.pickle
positive/data/kerr/note.rm
positive/data/kerr/l10/n0l10m0.dat
positive/data/kerr/l10/n0l10m1.dat
positive/data/kerr/l10/n0l10m10.dat
positive/data/kerr/l10/n0l10m2.dat
positive/data/kerr/l10/n0l10m3.dat
positive/data/kerr/l10/n0l10m4.dat
positive/data/kerr/l10/n0l10m5.dat
positive/data/kerr/l10/n0l10m6.dat
positive/data/kerr/l10/n0l10m7.dat
positive/data/kerr/l10/n0l10m8.dat
positive/data/kerr/l10/n0l10m9.dat
positive/data/kerr/l10/n0l10mm1.dat
positive/data/kerr/l10/n0l10mm10.dat
positive/data/kerr/l10/n0l10mm2.dat
positive/data/kerr/l10/n0l10mm3.dat
positive/data/kerr/l10/n0l10mm4.dat
positive/data/kerr/l10/n0l10mm5.dat
positive/data/kerr/l10/n0l10mm6.dat
positive/data/kerr/l10/n0l10mm7.dat
positive/data/kerr/l10/n0l10mm8.dat
positive/data/kerr/l10/n0l10mm9.dat
positive/data/kerr/l10/n1l10m0.dat
positive/data/kerr/l10/n1l10m1.dat
positive/data/kerr/l10/n1l10m10.dat
positive/data/kerr/l10/n1l10m2.dat
positive/data/kerr/l10/n1l10m3.dat
positive/data/kerr/l10/n1l10m4.dat
positive/data/kerr/l10/n1l10m5.dat
positive/data/kerr/l10/n1l10m6.dat
positive/data/kerr/l10/n1l10m7.dat
positive/data/kerr/l10/n1l10m8.dat
positive/data/kerr/l10/n1l10m9.dat
positive/data/kerr/l10/n1l10mm1.dat
positive/data/kerr/l10/n1l10mm10.dat
positive/data/kerr/l10/n1l10mm2.dat
positive/data/kerr/l10/n1l10mm3.dat
positive/data/kerr/l10/n1l10mm4.dat
positive/data/kerr/l10/n1l10mm5.dat
positive/data/kerr/l10/n1l10mm6.dat
positive/data/kerr/l10/n1l10mm7.dat
positive/data/kerr/l10/n1l10mm8.dat
positive/data/kerr/l10/n1l10mm9.dat
positive/data/kerr/l10/n2l10m0.dat
positive/data/kerr/l10/n2l10m1.dat
positive/data/kerr/l10/n2l10m10.dat
positive-1.0.dist-info/LICENSE
positive-1.0.dist-info/METADATA
positive-1.0.dist-info/WHEEL
positive-1.0.dist-info/top_level.txt
positive-1.0.dist-info/RECORD
