Metadata-Version: 2.1
Name: positive
Version: 1.0
Summary: Low level python API for NR+LIGO packages.
Home-page: https://github.com/llondon6/positive
Author: Lionel London
Author-email: lionel.london@ligo.org
License: MIT
Download-URL: https://github.com/llondon6/positive/archive/master.zip
Platform: UNKNOWN
Classifier: Programming Language :: Python :: 2.7
Classifier: Programming Language :: Python :: 3
Classifier: License :: OSI Approved :: MIT License
Classifier: Operating System :: OS Independent
Classifier: Intended Audience :: Science/Research
Classifier: Intended Audience :: Developers
Classifier: Topic :: Software Development
Classifier: Topic :: Scientific/Engineering
Requires-Dist: numpy
Requires-Dist: scipy
Requires-Dist: matplotlib
Requires-Dist: h5py
Requires-Dist: six
